{"openapi":"3.0.0","paths":{"/api/v1/auth/login":{"post":{"operationId":"AuthController_login","summary":"Login with email and password","parameters":[],"requestBody":{"required":true,"content":{"application/json":{"schema":{"$ref":"#/components/schemas/LoginDto"}}}},"responses":{"200":{"description":"Login successful"},"401":{"description":"Invalid credentials"}},"tags":["Authentication"]}},"/api/v1/auth/register":{"post":{"operationId":"AuthController_register","summary":"Register new user","parameters":[],"requestBody":{"required":true,"content":{"application/json":{"schema":{"$ref":"#/components/schemas/RegisterDto"}}}},"responses":{"201":{"description":"User registered successfully"},"400":{"description":"User already exists"}},"tags":["Authentication"]}},"/api/v1/auth/refresh":{"post":{"operationId":"AuthController_refresh","summary":"Refresh access token","parameters":[],"requestBody":{"required":true,"content":{"application/json":{"schema":{"$ref":"#/components/schemas/RefreshTokenDto"}}}},"responses":{"200":{"description":"Token refreshed successfully"},"401":{"description":"Invalid refresh token"}},"tags":["Authentication"]}},"/api/v1/auth/logout":{"post":{"operationId":"AuthController_logout","summary":"Logout user","parameters":[],"requestBody":{"required":true,"content":{"application/json":{"schema":{"$ref":"#/components/schemas/LogoutDto"}}}},"responses":{"200":{"description":"Logout successful"}},"tags":["Authentication"],"security":[{"bearer":[]}]}},"/api/v1/auth/profile":{"get":{"operationId":"AuthController_getProfile","summary":"Get current user profile with 3-level menu hierarchy","parameters":[],"responses":{"200":{"description":"Profile retrieved successfully with hierarchical menu structure","content":{"application/json":{"schema":{"$ref":"#/components/schemas/ProfileResponse"}}}}},"tags":["Authentication"],"security":[{"bearer":[]}]},"put":{"operationId":"AuthController_updateProfile","summary":"Update current user profile (excluding password)","parameters":[],"requestBody":{"required":true,"content":{"application/json":{"schema":{"$ref":"#/components/schemas/UpdateProfileDto"}}}},"responses":{"200":{"description":"Profile updated successfully"},"400":{"description":"Email or username already exists"},"401":{"description":"Unauthorized"}},"tags":["Authentication"],"security":[{"bearer":[]}]}},"/api/v1/auth/azure":{"get":{"operationId":"AuthController_azureLogin","summary":"Azure AD OAuth login","parameters":[],"responses":{"200":{"description":""}},"tags":["Authentication"]}},"/api/v1/auth/azure/callback":{"get":{"operationId":"AuthController_azureCallback","summary":"Azure AD OAuth callback","parameters":[],"responses":{"200":{"description":""}},"tags":["Authentication"]}},"/api/v1/users":{"post":{"operationId":"UserController_create","summary":"Create new user","parameters":[],"requestBody":{"required":true,"content":{"application/json":{"schema":{"$ref":"#/components/schemas/CreateUserDto"}}}},"responses":{"201":{"description":"User created successfully"},"400":{"description":"Bad request"}},"tags":["Users"],"security":[{"bearer":[]}]},"get":{"operationId":"UserController_findAll","summary":"Get all users with advanced filtering","parameters":[{"name":"page","required":false,"in":"query","description":"Page number","schema":{"type":"number"}},{"name":"limit","required":false,"in":"query","description":"Items per page","schema":{"type":"number"}},{"name":"search","required":false,"in":"query","description":"Search in email, first name, last name, username","schema":{"type":"string"}},{"name":"roleId","required":false,"in":"query","description":"Filter by role ID","schema":{"type":"string"}},{"name":"startDate","required":false,"in":"query","description":"Filter by creation date from (YYYY-MM-DD)","schema":{"type":"string"}},{"name":"endDate","required":false,"in":"query","description":"Filter by creation date to (YYYY-MM-DD)","schema":{"type":"string"}},{"name":"status","required":false,"in":"query","description":"Filter by status: active, inactive, all","schema":{"enum":["active","inactive","all"],"type":"string"}}],"responses":{"200":{"description":"Users retrieved successfully"}},"tags":["Users"],"security":[{"bearer":[]}]}},"/api/v1/users/export":{"get":{"operationId":"UserController_exportToExcel","summary":"Export users to Excel with filtering","parameters":[{"name":"search","required":false,"in":"query","description":"Search in email, first name, last name, username","schema":{"type":"string"}},{"name":"roleId","required":false,"in":"query","description":"Filter by role ID","schema":{"type":"string"}},{"name":"startDate","required":false,"in":"query","description":"Filter by creation date from (YYYY-MM-DD)","schema":{"type":"string"}},{"name":"endDate","required":false,"in":"query","description":"Filter by creation date to (YYYY-MM-DD)","schema":{"type":"string"}},{"name":"status","required":false,"in":"query","description":"Filter by status: active, inactive, all","schema":{"enum":["active","inactive","all"],"type":"string"}}],"responses":{"200":{"description":"Excel file generated successfully"}},"tags":["Users"],"security":[{"bearer":[]}]}},"/api/v1/users/{id}":{"get":{"operationId":"UserController_findOne","summary":"Get user by ID","parameters":[{"name":"id","required":true,"in":"path","schema":{"type":"string"}}],"responses":{"200":{"description":"User retrieved successfully"},"404":{"description":"User not found"}},"tags":["Users"],"security":[{"bearer":[]}]},"patch":{"operationId":"UserController_update","summary":"Update user","parameters":[{"name":"id","required":true,"in":"path","schema":{"type":"string"}}],"requestBody":{"required":true,"content":{"application/json":{"schema":{"$ref":"#/components/schemas/UpdateUserDto"}}}},"responses":{"200":{"description":"User updated successfully"},"404":{"description":"User not found"}},"tags":["Users"],"security":[{"bearer":[]}]},"delete":{"operationId":"UserController_remove","summary":"Delete user","parameters":[{"name":"id","required":true,"in":"path","schema":{"type":"string"}}],"responses":{"200":{"description":"User deleted successfully"},"404":{"description":"User not found"}},"tags":["Users"],"security":[{"bearer":[]}]}},"/api/v1/users/upload-avatar":{"post":{"operationId":"UserController_uploadAvatar","summary":"Upload avatar image and get URL","parameters":[],"requestBody":{"required":true,"description":"Avatar image file","content":{"multipart/form-data":{"schema":{"type":"object","properties":{"avatar":{"type":"string","format":"binary","description":"Avatar image file (JPEG, PNG, GIF, WebP, max 5MB)"}},"$ref":"#/components/schemas/"}}}},"responses":{"200":{"description":"Avatar uploaded successfully","content":{"application/json":{"schema":{"type":"object","properties":{"avatar_url":{"type":"string","description":"Full URL to the uploaded avatar image"},"avatar_path":{"type":"string","description":"Relative path to store in database"},"message":{"type":"string","description":"Success message"}}}}}},"400":{"description":"Invalid file or file too large"}},"tags":["Users"],"security":[{"bearer":[]}]}},"/api/v1/roles":{"post":{"operationId":"RoleController_create","summary":"Create a new role","parameters":[],"requestBody":{"required":true,"content":{"application/json":{"schema":{"$ref":"#/components/schemas/CreateRoleDto"}}}},"responses":{"201":{"description":""}},"tags":["Roles"],"security":[{"bearer":[]}]},"get":{"operationId":"RoleController_findAll","summary":"Get all roles","parameters":[{"name":"page","required":true,"in":"query","schema":{"type":"string"}},{"name":"limit","required":true,"in":"query","schema":{"type":"string"}},{"name":"search","required":true,"in":"query","schema":{"type":"string"}}],"responses":{"200":{"description":""}},"tags":["Roles"],"security":[{"bearer":[]}]}},"/api/v1/roles/export":{"get":{"operationId":"RoleController_exportToExcel","summary":"Export roles to Excel","parameters":[],"responses":{"200":{"description":""}},"tags":["Roles"],"security":[{"bearer":[]}]}},"/api/v1/roles/menus/permissions":{"get":{"operationId":"RoleController_getAllMenusWithPermissions","summary":"Get all menus with permissions for a role","parameters":[{"name":"roleId","required":true,"in":"query","schema":{"type":"string"}}],"responses":{"200":{"description":""}},"tags":["Roles"],"security":[{"bearer":[]}]},"post":{"operationId":"RoleController_updatePermissionsFromMenus","summary":"Update all permissions for a role from menu structure","parameters":[],"requestBody":{"required":true,"content":{"application/json":{"schema":{"$ref":"#/components/schemas/UpdatePermissionsFromMenusDto"}}}},"responses":{"201":{"description":""}},"tags":["Roles"],"security":[{"bearer":[]}]}},"/api/v1/roles/{id}":{"get":{"operationId":"RoleController_findOne","summary":"Get role by ID","parameters":[{"name":"id","required":true,"in":"path","schema":{"type":"string"}}],"responses":{"200":{"description":""}},"tags":["Roles"],"security":[{"bearer":[]}]},"patch":{"operationId":"RoleController_update","summary":"Update role","parameters":[{"name":"id","required":true,"in":"path","schema":{"type":"string"}}],"requestBody":{"required":true,"content":{"application/json":{"schema":{"$ref":"#/components/schemas/UpdateRoleDto"}}}},"responses":{"200":{"description":""}},"tags":["Roles"],"security":[{"bearer":[]}]},"delete":{"operationId":"RoleController_remove","summary":"Delete role","parameters":[{"name":"id","required":true,"in":"path","schema":{"type":"string"}}],"responses":{"200":{"description":""}},"tags":["Roles"],"security":[{"bearer":[]}]}},"/api/v1/roles/{id}/permissions":{"post":{"operationId":"RoleController_setPermissions","summary":"Set role permissions","parameters":[{"name":"id","required":true,"in":"path","schema":{"type":"string"}}],"requestBody":{"required":true,"content":{"application/json":{"schema":{"$ref":"#/components/schemas/SetPermissionsDto"}}}},"responses":{"201":{"description":""}},"tags":["Roles"],"security":[{"bearer":[]}]},"get":{"operationId":"RoleController_getPermissions","summary":"Get role permissions","parameters":[{"name":"id","required":true,"in":"path","schema":{"type":"string"}}],"responses":{"200":{"description":""}},"tags":["Roles"],"security":[{"bearer":[]}]}},"/api/v1/roles/test-validation":{"post":{"operationId":"RoleController_testValidation","summary":"Test validation","parameters":[],"requestBody":{"required":true,"content":{"application/json":{"schema":{"$ref":"#/components/schemas/TestValidationDto"}}}},"responses":{"201":{"description":""}},"tags":["Roles"],"security":[{"bearer":[]}]}},"/api/v1/menu":{"post":{"operationId":"MenuController_create","summary":"Create a new menu","parameters":[],"requestBody":{"required":true,"content":{"application/json":{"schema":{"$ref":"#/components/schemas/CreateMenuDto"}}}},"responses":{"201":{"description":""}},"tags":["Menu"],"security":[{"bearer":[]}]},"get":{"operationId":"MenuController_findAll","summary":"Get all menus","parameters":[],"responses":{"200":{"description":""}},"tags":["Menu"],"security":[{"bearer":[]}]}},"/api/v1/menu/navigation":{"get":{"operationId":"MenuController_getNavigation","summary":"Get navigation menu by language","parameters":[{"name":"lang","required":false,"in":"query","description":"Language code (default: en)","schema":{"type":"string"}}],"responses":{"200":{"description":""}},"tags":["Menu"],"security":[{"bearer":[]}]}},"/api/v1/menu/navigation/public":{"get":{"operationId":"MenuController_getPublicNavigation","summary":"Get navigation menu by language","parameters":[{"name":"lang","required":false,"in":"query","description":"Language code (default: en)","schema":{"type":"string"}}],"responses":{"200":{"description":""}},"tags":["Menu"],"security":[{"bearer":[]}]}},"/api/v1/menu/tree":{"get":{"operationId":"MenuController_getMenuTree","summary":"Get menu tree structure for current user","parameters":[],"responses":{"200":{"description":""}},"tags":["Menu"],"security":[{"bearer":[]}]}},"/api/v1/menu/user":{"get":{"operationId":"MenuController_findByUserRole","summary":"Get menus for current user role","parameters":[],"responses":{"200":{"description":""}},"tags":["Menu"],"security":[{"bearer":[]}]}},"/api/v1/menu/{id}":{"get":{"operationId":"MenuController_findOne","summary":"Get menu by ID","parameters":[{"name":"id","required":true,"in":"path","description":"Menu ID","schema":{"type":"string"}}],"responses":{"200":{"description":""}},"tags":["Menu"],"security":[{"bearer":[]}]},"patch":{"operationId":"MenuController_update","summary":"Update menu","parameters":[{"name":"id","required":true,"in":"path","description":"Menu ID","schema":{"type":"string"}}],"requestBody":{"required":true,"content":{"application/json":{"schema":{"$ref":"#/components/schemas/UpdateMenuDto"}}}},"responses":{"200":{"description":""}},"tags":["Menu"],"security":[{"bearer":[]}]},"delete":{"operationId":"MenuController_remove","summary":"Delete menu","parameters":[{"name":"id","required":true,"in":"path","description":"Menu ID","schema":{"type":"string"}}],"responses":{"204":{"description":""}},"tags":["Menu"],"security":[{"bearer":[]}]}},"/api/v1/menu/{id}/translations":{"post":{"operationId":"MenuController_addTranslation","summary":"Add translation to menu","parameters":[{"name":"id","required":true,"in":"path","description":"Menu ID","schema":{"type":"string"}}],"requestBody":{"required":true,"content":{"application/json":{"schema":{"$ref":"#/components/schemas/CreateMenuTranslationDto"}}}},"responses":{"201":{"description":""}},"tags":["Menu"],"security":[{"bearer":[]}]}},"/api/v1/menu/{id}/translations/{translationId}":{"patch":{"operationId":"MenuController_updateTranslation","summary":"Update menu translation","parameters":[{"name":"id","required":true,"in":"path","description":"Menu ID","schema":{"type":"string"}},{"name":"translationId","required":true,"in":"path","description":"Translation ID","schema":{"type":"string"}}],"requestBody":{"required":true,"content":{"application/json":{"schema":{"$ref":"#/components/schemas/CreateMenuTranslationDto"}}}},"responses":{"200":{"description":""}},"tags":["Menu"],"security":[{"bearer":[]}]},"delete":{"operationId":"MenuController_removeTranslation","summary":"Delete menu translation","parameters":[{"name":"id","required":true,"in":"path","description":"Menu ID","schema":{"type":"string"}},{"name":"translationId","required":true,"in":"path","description":"Translation ID","schema":{"type":"string"}}],"responses":{"204":{"description":""}},"tags":["Menu"],"security":[{"bearer":[]}]}},"/api/v1/permissions":{"get":{"operationId":"PermissionController_findAll","summary":"Get all permissions from sys_menu table","parameters":[{"name":"page","required":true,"in":"query","schema":{"type":"string"}},{"name":"limit","required":true,"in":"query","schema":{"type":"string"}},{"name":"search","required":true,"in":"query","schema":{"type":"string"}}],"responses":{"200":{"description":""}},"tags":["Permissions"],"security":[{"bearer":[]}]}},"/api/v1/categories":{"get":{"operationId":"CategoryController_findAll","summary":"Get all categories with filtering","parameters":[{"name":"page","required":false,"in":"query","description":"Page number (default: 1)","schema":{"example":1,"type":"number"}},{"name":"limit","required":false,"in":"query","description":"Items per page (default: 10)","schema":{"example":10,"type":"number"}},{"name":"name","required":false,"in":"query","description":"Filter by name","schema":{"example":"example name","type":"string"}},{"name":"status","required":false,"in":"query","description":"Filter by status","schema":{"example":"active","type":"string"}},{"name":"startDate","required":false,"in":"query","description":"Start date for filtering (ISO 8601 format)","schema":{"example":"2024-01-01T00:00:00.000Z","type":"string"}},{"name":"endDate","required":false,"in":"query","description":"End date for filtering (ISO 8601 format)","schema":{"example":"2024-12-31T23:59:59.999Z","type":"string"}},{"name":"slug","required":false,"in":"query","description":"Filter by slug","schema":{"example":"example-slug","type":"string"}},{"name":"lang","required":false,"in":"query","description":"Language code (en, th)","schema":{"type":"string"}}],"responses":{"200":{"description":"Categories retrieved successfully"}},"tags":["Categories"],"security":[{"bearer":[]}]},"post":{"operationId":"CategoryController_create","summary":"Create new category","parameters":[],"requestBody":{"required":true,"content":{"application/json":{"schema":{"$ref":"#/components/schemas/CreateCategoryDto"}}}},"responses":{"201":{"description":""}},"tags":["Categories"],"security":[{"bearer":[]}]}},"/api/v1/categories/export":{"get":{"operationId":"CategoryController_exportToExcel","summary":"Export categories to Excel with filtering","parameters":[{"name":"page","required":false,"in":"query","description":"Page number (default: 1)","schema":{"example":1,"type":"number"}},{"name":"limit","required":false,"in":"query","description":"Items per page (default: 10)","schema":{"example":10,"type":"number"}},{"name":"name","required":false,"in":"query","description":"Filter by name","schema":{"example":"example name","type":"string"}},{"name":"status","required":false,"in":"query","description":"Filter by status","schema":{"example":"active","type":"string"}},{"name":"startDate","required":false,"in":"query","description":"Start date for filtering (ISO 8601 format)","schema":{"example":"2024-01-01T00:00:00.000Z","type":"string"}},{"name":"endDate","required":false,"in":"query","description":"End date for filtering (ISO 8601 format)","schema":{"example":"2024-12-31T23:59:59.999Z","type":"string"}},{"name":"slug","required":false,"in":"query","description":"Filter by slug","schema":{"example":"example-slug","type":"string"}}],"responses":{"200":{"description":"Excel file generated successfully"}},"tags":["Categories"],"security":[{"bearer":[]}]}},"/api/v1/categories/{id}":{"get":{"operationId":"CategoryController_findOne","summary":"Get category by ID","parameters":[{"name":"id","required":true,"in":"path","schema":{"type":"string"}},{"name":"lang","required":false,"in":"query","description":"Language code (en, th)","schema":{"type":"string"}}],"responses":{"200":{"description":""}},"tags":["Categories"],"security":[{"bearer":[]}]},"put":{"operationId":"CategoryController_update","summary":"Update category","parameters":[{"name":"id","required":true,"in":"path","schema":{"type":"string"}}],"requestBody":{"required":true,"content":{"application/json":{"schema":{"$ref":"#/components/schemas/UpdateCategoryDto"}}}},"responses":{"200":{"description":""}},"tags":["Categories"],"security":[{"bearer":[]}]},"delete":{"operationId":"CategoryController_remove","summary":"Delete category","parameters":[{"name":"id","required":true,"in":"path","schema":{"type":"string"}}],"responses":{"200":{"description":""}},"tags":["Categories"],"security":[{"bearer":[]}]}},"/api/v1/categories/slug/{slug}":{"get":{"operationId":"CategoryController_findBySlug","summary":"Get category by slug","parameters":[{"name":"slug","required":true,"in":"path","schema":{"type":"string"}},{"name":"lang","required":false,"in":"query","description":"Language code (en, th)","schema":{"type":"string"}}],"responses":{"200":{"description":""}},"tags":["Categories"],"security":[{"bearer":[]}]}},"/api/v1/categories/{id}/translations":{"post":{"operationId":"CategoryController_upsertTranslation","summary":"Add or update category translation","parameters":[{"name":"id","required":true,"in":"path","schema":{"type":"string"}}],"requestBody":{"required":true,"content":{"application/json":{"schema":{"$ref":"#/components/schemas/CreateCategoryTranslationDto"}}}},"responses":{"201":{"description":""}},"tags":["Categories"],"security":[{"bearer":[]}]}},"/api/v1/categories/public/list":{"get":{"operationId":"CategoryController_findPublic","summary":"Get active categories","parameters":[{"name":"lang","required":false,"in":"query","description":"Language code (en, th)","schema":{"type":"string"}}],"responses":{"200":{"description":""}},"tags":["Categories"],"security":[{"bearer":[]}]}},"/api/v1/contents":{"get":{"operationId":"ContentController_findAll","summary":"Get all contents","parameters":[{"name":"lang","required":false,"in":"query","description":"Language code (en, th)","schema":{"type":"string"}},{"name":"category","required":false,"in":"query","description":"Category ID","schema":{"type":"string"}},{"name":"status","required":false,"in":"query","description":"Content status","schema":{"type":"string"}}],"responses":{"200":{"description":""}},"tags":["Contents"],"security":[{"bearer":[]}]},"post":{"operationId":"ContentController_create","summary":"Create new content","parameters":[],"requestBody":{"required":true,"content":{"application/json":{"schema":{"$ref":"#/components/schemas/CreateContentDto"}}}},"responses":{"201":{"description":""}},"tags":["Contents"],"security":[{"bearer":[]}]}},"/api/v1/contents/{id}":{"get":{"operationId":"ContentController_findOne","summary":"Get content by ID","parameters":[{"name":"id","required":true,"in":"path","schema":{"type":"string"}},{"name":"lang","required":false,"in":"query","description":"Language code (en, th)","schema":{"type":"string"}}],"responses":{"200":{"description":""}},"tags":["Contents"],"security":[{"bearer":[]}]},"put":{"operationId":"ContentController_update","summary":"Update content","parameters":[{"name":"id","required":true,"in":"path","schema":{"type":"string"}}],"requestBody":{"required":true,"content":{"application/json":{"schema":{"$ref":"#/components/schemas/UpdateContentDto"}}}},"responses":{"200":{"description":""}},"tags":["Contents"],"security":[{"bearer":[]}]},"delete":{"operationId":"ContentController_remove","summary":"Delete content","parameters":[{"name":"id","required":true,"in":"path","schema":{"type":"string"}}],"responses":{"200":{"description":""}},"tags":["Contents"],"security":[{"bearer":[]}]}},"/api/v1/contents/slug/{slug}":{"get":{"operationId":"ContentController_findBySlug","summary":"Get content by slug","parameters":[{"name":"slug","required":true,"in":"path","schema":{"type":"string"}},{"name":"lang","required":false,"in":"query","description":"Language code (en, th)","schema":{"type":"string"}}],"responses":{"200":{"description":""}},"tags":["Contents"],"security":[{"bearer":[]}]}},"/api/v1/contents/{id}/translations":{"post":{"operationId":"ContentController_upsertTranslation","summary":"Add or update content translation","parameters":[{"name":"id","required":true,"in":"path","schema":{"type":"string"}}],"requestBody":{"required":true,"content":{"application/json":{"schema":{"$ref":"#/components/schemas/CreateContentTranslationDto"}}}},"responses":{"201":{"description":""}},"tags":["Contents"],"security":[{"bearer":[]}]}},"/api/v1/contents/published/list":{"get":{"operationId":"ContentController_findPublished","summary":"Get published contents","parameters":[{"name":"lang","required":false,"in":"query","description":"Language code (en, th)","schema":{"type":"string"}},{"name":"category","required":false,"in":"query","description":"Category slug","schema":{"type":"string"}}],"responses":{"200":{"description":""}},"tags":["Contents"],"security":[{"bearer":[]}]}},"/api/v1/labels":{"post":{"operationId":"LabelController_create","summary":"Create a new label","parameters":[],"requestBody":{"required":true,"content":{"application/json":{"schema":{"$ref":"#/components/schemas/CreateLabelDto"}}}},"responses":{"201":{"description":""}},"tags":["Labels"],"security":[{"bearer":[]}]},"get":{"operationId":"LabelController_findAll","summary":"Get all labels","parameters":[],"responses":{"200":{"description":""}},"tags":["Labels"],"security":[{"bearer":[]}]}},"/api/v1/labels/by-language":{"get":{"operationId":"LabelController_findByLanguage","summary":"Get labels by language","parameters":[{"name":"lang","required":false,"in":"query","description":"Language code (default: en)","schema":{"type":"string"}}],"responses":{"200":{"description":""}},"tags":["Labels"],"security":[{"bearer":[]}]}},"/api/v1/labels/{id}":{"get":{"operationId":"LabelController_findOne","summary":"Get label by ID","parameters":[{"name":"id","required":true,"in":"path","description":"Label ID","schema":{"type":"string"}}],"responses":{"200":{"description":""}},"tags":["Labels"],"security":[{"bearer":[]}]},"patch":{"operationId":"LabelController_update","summary":"Update label","parameters":[{"name":"id","required":true,"in":"path","description":"Label ID","schema":{"type":"string"}}],"requestBody":{"required":true,"content":{"application/json":{"schema":{"$ref":"#/components/schemas/UpdateLabelDto"}}}},"responses":{"200":{"description":""}},"tags":["Labels"],"security":[{"bearer":[]}]},"delete":{"operationId":"LabelController_remove","summary":"Delete label","parameters":[{"name":"id","required":true,"in":"path","description":"Label ID","schema":{"type":"string"}}],"responses":{"204":{"description":""}},"tags":["Labels"],"security":[{"bearer":[]}]}},"/api/v1/labels/{id}/translations":{"post":{"operationId":"LabelController_addTranslation","summary":"Add translation to label","parameters":[{"name":"id","required":true,"in":"path","description":"Label ID","schema":{"type":"string"}}],"requestBody":{"required":true,"content":{"application/json":{"schema":{"$ref":"#/components/schemas/CreateLabelTranslationDto"}}}},"responses":{"201":{"description":""}},"tags":["Labels"],"security":[{"bearer":[]}]}},"/api/v1/labels/{id}/translations/{translationId}":{"patch":{"operationId":"LabelController_updateTranslation","summary":"Update label translation","parameters":[{"name":"id","required":true,"in":"path","description":"Label ID","schema":{"type":"string"}},{"name":"translationId","required":true,"in":"path","description":"Translation ID","schema":{"type":"string"}}],"requestBody":{"required":true,"content":{"application/json":{"schema":{"$ref":"#/components/schemas/CreateLabelTranslationDto"}}}},"responses":{"200":{"description":""}},"tags":["Labels"],"security":[{"bearer":[]}]},"delete":{"operationId":"LabelController_removeTranslation","summary":"Delete label translation","parameters":[{"name":"id","required":true,"in":"path","description":"Label ID","schema":{"type":"string"}},{"name":"translationId","required":true,"in":"path","description":"Translation ID","schema":{"type":"string"}}],"responses":{"204":{"description":""}},"tags":["Labels"],"security":[{"bearer":[]}]}},"/api/v1/languages":{"post":{"operationId":"LanguageController_create","summary":"Create a new language","parameters":[],"requestBody":{"required":true,"content":{"application/json":{"schema":{"$ref":"#/components/schemas/CreateLanguageDto"}}}},"responses":{"201":{"description":""}},"tags":["Languages"],"security":[{"bearer":[]}]},"get":{"operationId":"LanguageController_findAll","summary":"Get all languages","parameters":[{"name":"page","required":true,"in":"query","schema":{"type":"string"}},{"name":"limit","required":true,"in":"query","schema":{"type":"string"}},{"name":"search","required":true,"in":"query","schema":{"type":"string"}}],"responses":{"200":{"description":""}},"tags":["Languages"],"security":[{"bearer":[]}]}},"/api/v1/languages/default":{"get":{"operationId":"LanguageController_getDefault","summary":"Get default language","parameters":[],"responses":{"200":{"description":""}},"tags":["Languages"],"security":[{"bearer":[]}]}},"/api/v1/languages/{id}":{"get":{"operationId":"LanguageController_findOne","summary":"Get language by ID","parameters":[{"name":"id","required":true,"in":"path","schema":{"type":"string"}}],"responses":{"200":{"description":""}},"tags":["Languages"],"security":[{"bearer":[]}]},"patch":{"operationId":"LanguageController_update","summary":"Update language","parameters":[{"name":"id","required":true,"in":"path","schema":{"type":"string"}}],"requestBody":{"required":true,"content":{"application/json":{"schema":{"$ref":"#/components/schemas/UpdateLanguageDto"}}}},"responses":{"200":{"description":""}},"tags":["Languages"],"security":[{"bearer":[]}]},"delete":{"operationId":"LanguageController_remove","summary":"Delete language","parameters":[{"name":"id","required":true,"in":"path","schema":{"type":"string"}}],"responses":{"200":{"description":""}},"tags":["Languages"],"security":[{"bearer":[]}]}},"/api/v1/languages/set-default":{"post":{"operationId":"LanguageController_setDefault","summary":"Set default language","parameters":[],"requestBody":{"required":true,"content":{"application/json":{"schema":{"$ref":"#/components/schemas/SetDefaultLanguageDto"}}}},"responses":{"201":{"description":""}},"tags":["Languages"],"security":[{"bearer":[]}]}},"/api/v1/settings":{"post":{"operationId":"SettingsController_create","summary":"Create a new setting","parameters":[],"requestBody":{"required":true,"content":{"application/json":{"schema":{"$ref":"#/components/schemas/CreateSettingDto"}}}},"responses":{"201":{"description":""}},"tags":["Settings"],"security":[{"bearer":[]}]},"get":{"operationId":"SettingsController_findAll","summary":"Get all settings","parameters":[{"name":"page","required":true,"in":"query","schema":{"type":"string"}},{"name":"limit","required":true,"in":"query","schema":{"type":"string"}},{"name":"search","required":true,"in":"query","schema":{"type":"string"}}],"responses":{"200":{"description":""}},"tags":["Settings"],"security":[{"bearer":[]}]}},"/api/v1/settings/{id}":{"get":{"operationId":"SettingsController_findOne","summary":"Get setting by ID","parameters":[{"name":"id","required":true,"in":"path","schema":{"type":"string"}}],"responses":{"200":{"description":""}},"tags":["Settings"],"security":[{"bearer":[]}]},"patch":{"operationId":"SettingsController_update","summary":"Update setting","parameters":[{"name":"id","required":true,"in":"path","schema":{"type":"string"}}],"requestBody":{"required":true,"content":{"application/json":{"schema":{"$ref":"#/components/schemas/UpdateSettingDto"}}}},"responses":{"200":{"description":""}},"tags":["Settings"],"security":[{"bearer":[]}]},"delete":{"operationId":"SettingsController_remove","summary":"Delete setting","parameters":[{"name":"id","required":true,"in":"path","schema":{"type":"string"}}],"responses":{"200":{"description":""}},"tags":["Settings"],"security":[{"bearer":[]}]}},"/api/v1/notifications":{"get":{"operationId":"NotificationController_findByUser","summary":"Get user notifications","parameters":[],"responses":{"200":{"description":""}},"tags":["Notifications"],"security":[{"bearer":[]}]}},"/api/v1/notifications/{id}/read":{"patch":{"operationId":"NotificationController_markAsRead","summary":"Mark notification as read","parameters":[{"name":"id","required":true,"in":"path","schema":{"type":"string"}}],"responses":{"200":{"description":""}},"tags":["Notifications"],"security":[{"bearer":[]}]}},"/api/v1/audit/logs":{"get":{"operationId":"AuditController_findAll","summary":"Get audit logs","parameters":[{"name":"page","required":false,"in":"query","schema":{"type":"number"}},{"name":"limit","required":false,"in":"query","schema":{"type":"number"}}],"responses":{"200":{"description":""}},"tags":["Audit"],"security":[{"bearer":[]}]}},"/api/v1/audit/logs/export":{"get":{"operationId":"AuditController_exportAuditLogs","summary":"Export audit logs to Excel","parameters":[],"responses":{"200":{"description":"Excel file generated successfully"}},"tags":["Audit"],"security":[{"bearer":[]}]}},"/api/v1/audit/activity":{"get":{"operationId":"AuditController_findActivityLogs","summary":"Get activity logs","parameters":[{"name":"page","required":false,"in":"query","schema":{"type":"number"}},{"name":"limit","required":false,"in":"query","schema":{"type":"number"}}],"responses":{"200":{"description":""}},"tags":["Audit"],"security":[{"bearer":[]}]}},"/api/v1/audit/activity/export":{"get":{"operationId":"AuditController_exportActivityLogs","summary":"Export activity logs to Excel","parameters":[],"responses":{"200":{"description":"Excel file generated successfully"}},"tags":["Audit"],"security":[{"bearer":[]}]}},"/api/v1/configuration":{"post":{"operationId":"ConfigurationController_create","parameters":[],"requestBody":{"required":true,"content":{"application/json":{"schema":{"$ref":"#/components/schemas/CreateConfigurationDto"}}}},"responses":{"201":{"description":""}},"tags":["Configuration"]},"get":{"operationId":"ConfigurationController_findAll","parameters":[],"responses":{"200":{"description":""}},"tags":["Configuration"]}},"/api/v1/configuration/{id}":{"get":{"operationId":"ConfigurationController_findOne","parameters":[{"name":"id","required":true,"in":"path","schema":{"type":"string"}}],"responses":{"200":{"description":""}},"tags":["Configuration"]},"patch":{"operationId":"ConfigurationController_update","parameters":[{"name":"id","required":true,"in":"path","schema":{"type":"string"}}],"requestBody":{"required":true,"content":{"application/json":{"schema":{"$ref":"#/components/schemas/UpdateConfigurationDto"}}}},"responses":{"200":{"description":""}},"tags":["Configuration"]},"delete":{"operationId":"ConfigurationController_remove","parameters":[{"name":"id","required":true,"in":"path","schema":{"type":"string"}}],"responses":{"200":{"description":""}},"tags":["Configuration"]}},"/api/v1/configuration/key/{key}":{"get":{"operationId":"ConfigurationController_findByKey","parameters":[{"name":"key","required":true,"in":"path","schema":{"type":"string"}}],"responses":{"200":{"description":""}},"tags":["Configuration"]}},"/api/v1/contact-form":{"post":{"operationId":"ContactFormController_create","summary":"Submit a contact form","parameters":[],"requestBody":{"required":true,"content":{"application/json":{"schema":{"$ref":"#/components/schemas/CreateContactFormDto"}}}},"responses":{"201":{"description":"Contact form submitted successfully","content":{"application/json":{"schema":{"$ref":"#/components/schemas/ContactFormResponse"}}}}},"tags":["Contact Form"],"security":[{"bearer":[]}]},"get":{"operationId":"ContactFormController_findAll","summary":"Get all contact forms with filtering","parameters":[{"name":"page","required":false,"in":"query","description":"Page number (default: 1)","schema":{"example":1,"type":"number"}},{"name":"limit","required":false,"in":"query","description":"Items per page (default: 10)","schema":{"example":10,"type":"number"}},{"name":"name","required":false,"in":"query","description":"Filter by name","schema":{"example":"example name","type":"string"}},{"name":"status","required":false,"in":"query","description":"Filter by status","schema":{"example":"active","type":"string"}},{"name":"startDate","required":false,"in":"query","description":"Start date for filtering (ISO 8601 format)","schema":{"example":"2024-01-01T00:00:00.000Z","type":"string"}},{"name":"endDate","required":false,"in":"query","description":"End date for filtering (ISO 8601 format)","schema":{"example":"2024-12-31T23:59:59.999Z","type":"string"}},{"name":"firstName","required":false,"in":"query","description":"Filter by first name","schema":{"example":"John","type":"string"}},{"name":"lastName","required":false,"in":"query","description":"Filter by last name","schema":{"example":"Doe","type":"string"}},{"name":"email","required":false,"in":"query","description":"Filter by email","schema":{"example":"john@example.com","type":"string"}}],"responses":{"200":{"description":"Contact forms retrieved successfully"}},"tags":["Contact Form"],"security":[{"bearer":[]}]}},"/api/v1/contact-form/export":{"get":{"operationId":"ContactFormController_exportToExcel","summary":"Export contact forms to Excel with filtering","parameters":[{"name":"page","required":false,"in":"query","description":"Page number (default: 1)","schema":{"example":1,"type":"number"}},{"name":"limit","required":false,"in":"query","description":"Items per page (default: 10)","schema":{"example":10,"type":"number"}},{"name":"name","required":false,"in":"query","description":"Filter by name","schema":{"example":"example name","type":"string"}},{"name":"status","required":false,"in":"query","description":"Filter by status","schema":{"example":"active","type":"string"}},{"name":"startDate","required":false,"in":"query","description":"Start date for filtering (ISO 8601 format)","schema":{"example":"2024-01-01T00:00:00.000Z","type":"string"}},{"name":"endDate","required":false,"in":"query","description":"End date for filtering (ISO 8601 format)","schema":{"example":"2024-12-31T23:59:59.999Z","type":"string"}},{"name":"firstName","required":false,"in":"query","description":"Filter by first name","schema":{"example":"John","type":"string"}},{"name":"lastName","required":false,"in":"query","description":"Filter by last name","schema":{"example":"Doe","type":"string"}},{"name":"email","required":false,"in":"query","description":"Filter by email","schema":{"example":"john@example.com","type":"string"}}],"responses":{"200":{"description":"Excel file generated successfully"}},"tags":["Contact Form"],"security":[{"bearer":[]}]}},"/api/v1/contact-form/statistics":{"get":{"operationId":"ContactFormController_getStatistics","summary":"Get contact form statistics","parameters":[],"responses":{"200":{"description":"Statistics retrieved successfully"}},"tags":["Contact Form"],"security":[{"bearer":[]}]}},"/api/v1/contact-form/{id}":{"get":{"operationId":"ContactFormController_findOne","summary":"Get contact form by ID","parameters":[{"name":"id","required":true,"in":"path","description":"Contact form ID","schema":{"type":"string"}}],"responses":{"200":{"description":"Contact form retrieved successfully","content":{"application/json":{"schema":{"$ref":"#/components/schemas/ContactFormResponse"}}}}},"tags":["Contact Form"],"security":[{"bearer":[]}]},"patch":{"operationId":"ContactFormController_update","summary":"Update contact form","parameters":[{"name":"id","required":true,"in":"path","description":"Contact form ID","schema":{"type":"string"}}],"requestBody":{"required":true,"content":{"application/json":{"schema":{"$ref":"#/components/schemas/UpdateContactFormDto"}}}},"responses":{"200":{"description":"Contact form updated successfully","content":{"application/json":{"schema":{"$ref":"#/components/schemas/ContactFormResponse"}}}}},"tags":["Contact Form"],"security":[{"bearer":[]}]},"delete":{"operationId":"ContactFormController_remove","summary":"Delete contact form","parameters":[{"name":"id","required":true,"in":"path","description":"Contact form ID","schema":{"type":"string"}}],"responses":{"204":{"description":"Contact form deleted successfully"}},"tags":["Contact Form"],"security":[{"bearer":[]}]}},"/api/v1/penthouses":{"post":{"operationId":"PenthousesController_create","summary":"Create a new penthouse","parameters":[],"requestBody":{"required":true,"content":{"application/json":{"schema":{"$ref":"#/components/schemas/CreatePenthouseDto"}}}},"responses":{"201":{"description":"Penthouse created successfully","content":{"application/json":{"schema":{"$ref":"#/components/schemas/PenthouseResponse"}}}}},"tags":["Penthouses"],"security":[{"bearer":[]}]},"get":{"operationId":"PenthousesController_findAll","summary":"Get all penthouses","parameters":[{"name":"page","required":false,"in":"query","description":"Page number (default: 1)","schema":{"type":"number"}},{"name":"limit","required":false,"in":"query","description":"Items per page (default: 10)","schema":{"type":"number"}},{"name":"status","required":false,"in":"query","description":"Filter by status","schema":{"type":"string"}},{"name":"locationId","required":false,"in":"query","description":"Filter by location ID","schema":{"type":"string"}},{"name":"propertyTypeId","required":false,"in":"query","description":"Filter by property type ID","schema":{"type":"string"}}],"responses":{"200":{"description":"Penthouses retrieved successfully"}},"tags":["Penthouses"]}},"/api/v1/penthouses/statistics":{"get":{"operationId":"PenthousesController_getStatistics","summary":"Get penthouse statistics","parameters":[],"responses":{"200":{"description":"Statistics retrieved successfully"}},"tags":["Penthouses"],"security":[{"bearer":[]}]}},"/api/v1/penthouses/{id}":{"get":{"operationId":"PenthousesController_findOne","summary":"Get penthouse by ID","parameters":[{"name":"id","required":true,"in":"path","description":"Penthouse ID","schema":{"type":"string"}}],"responses":{"200":{"description":"Penthouse retrieved successfully","content":{"application/json":{"schema":{"$ref":"#/components/schemas/PenthouseResponse"}}}}},"tags":["Penthouses"]},"patch":{"operationId":"PenthousesController_update","summary":"Update penthouse","parameters":[{"name":"id","required":true,"in":"path","description":"Penthouse ID","schema":{"type":"string"}}],"requestBody":{"required":true,"content":{"application/json":{"schema":{"$ref":"#/components/schemas/UpdatePenthouseDto"}}}},"responses":{"200":{"description":"Penthouse updated successfully","content":{"application/json":{"schema":{"$ref":"#/components/schemas/PenthouseResponse"}}}}},"tags":["Penthouses"],"security":[{"bearer":[]}]},"delete":{"operationId":"PenthousesController_remove","summary":"Delete penthouse","parameters":[{"name":"id","required":true,"in":"path","description":"Penthouse ID","schema":{"type":"string"}}],"responses":{"204":{"description":"Penthouse deleted successfully"}},"tags":["Penthouses"],"security":[{"bearer":[]}]}},"/api/v1/penthouses/{id}/publish":{"patch":{"operationId":"PenthousesController_publish","summary":"Publish penthouse","parameters":[{"name":"id","required":true,"in":"path","description":"Penthouse ID","schema":{"type":"string"}}],"responses":{"200":{"description":"Penthouse published successfully","content":{"application/json":{"schema":{"$ref":"#/components/schemas/PenthouseResponse"}}}}},"tags":["Penthouses"],"security":[{"bearer":[]}]}},"/api/v1/penthouses/{id}/unpublish":{"patch":{"operationId":"PenthousesController_unpublish","summary":"Unpublish penthouse (set to draft)","parameters":[{"name":"id","required":true,"in":"path","description":"Penthouse ID","schema":{"type":"string"}}],"responses":{"200":{"description":"Penthouse unpublished successfully","content":{"application/json":{"schema":{"$ref":"#/components/schemas/PenthouseResponse"}}}}},"tags":["Penthouses"],"security":[{"bearer":[]}]}},"/api/v1/penthouses/{id}/archive":{"patch":{"operationId":"PenthousesController_archive","summary":"Archive penthouse","parameters":[{"name":"id","required":true,"in":"path","description":"Penthouse ID","schema":{"type":"string"}}],"responses":{"200":{"description":"Penthouse archived successfully","content":{"application/json":{"schema":{"$ref":"#/components/schemas/PenthouseResponse"}}}}},"tags":["Penthouses"],"security":[{"bearer":[]}]}},"/api/v1/penthouses/{id}/detail":{"get":{"operationId":"PenthousesController_getDetail","summary":"Get detailed penthouse information","parameters":[{"name":"id","required":true,"in":"path","description":"Penthouse ID","schema":{"type":"string"}},{"name":"lang","required":false,"in":"query","description":"Language code (default: en)","schema":{"type":"string"}}],"responses":{"200":{"description":"Detailed penthouse information retrieved successfully"}},"tags":["Penthouses"]}},"/api/v1/penthouses-location":{"post":{"operationId":"PenthousesLocationController_create","summary":"Create a new location","parameters":[],"requestBody":{"required":true,"content":{"application/json":{"schema":{"$ref":"#/components/schemas/CreatePenthousesLocationDto"}}}},"responses":{"201":{"description":"Location created successfully","content":{"application/json":{"schema":{"$ref":"#/components/schemas/PenthousesLocationResponse"}}}}},"tags":["Penthouses Location"],"security":[{"bearer":[]}]},"get":{"operationId":"PenthousesLocationController_findAll","summary":"Get all locations","parameters":[{"name":"page","required":false,"in":"query","description":"Page number (default: 1)","schema":{"type":"number"}},{"name":"limit","required":false,"in":"query","description":"Items per page (default: 10)","schema":{"type":"number"}}],"responses":{"200":{"description":"Locations retrieved successfully"}},"tags":["Penthouses Location"]}},"/api/v1/penthouses-location/{id}":{"get":{"operationId":"PenthousesLocationController_findOne","summary":"Get location by ID","parameters":[{"name":"id","required":true,"in":"path","description":"Location ID","schema":{"type":"string"}}],"responses":{"200":{"description":"Location retrieved successfully","content":{"application/json":{"schema":{"$ref":"#/components/schemas/PenthousesLocationResponse"}}}}},"tags":["Penthouses Location"]},"patch":{"operationId":"PenthousesLocationController_update","summary":"Update location","parameters":[{"name":"id","required":true,"in":"path","description":"Location ID","schema":{"type":"string"}}],"requestBody":{"required":true,"content":{"application/json":{"schema":{"$ref":"#/components/schemas/UpdatePenthousesLocationDto"}}}},"responses":{"200":{"description":"Location updated successfully","content":{"application/json":{"schema":{"$ref":"#/components/schemas/PenthousesLocationResponse"}}}}},"tags":["Penthouses Location"],"security":[{"bearer":[]}]},"delete":{"operationId":"PenthousesLocationController_remove","summary":"Delete location","parameters":[{"name":"id","required":true,"in":"path","description":"Location ID","schema":{"type":"string"}}],"responses":{"204":{"description":"Location deleted successfully"}},"tags":["Penthouses Location"],"security":[{"bearer":[]}]}},"/api/v1/penthouses-property-type":{"post":{"operationId":"PenthousesPropertyTypeController_create","summary":"Create a new property type","parameters":[],"requestBody":{"required":true,"content":{"application/json":{"schema":{"$ref":"#/components/schemas/CreatePenthousesPropertyTypeDto"}}}},"responses":{"201":{"description":"Property type created successfully","content":{"application/json":{"schema":{"$ref":"#/components/schemas/PenthousesPropertyTypeResponse"}}}}},"tags":["Penthouses Property Type"],"security":[{"bearer":[]}]},"get":{"operationId":"PenthousesPropertyTypeController_findAll","summary":"Get all property types","parameters":[{"name":"page","required":false,"in":"query","description":"Page number (default: 1)","schema":{"type":"number"}},{"name":"limit","required":false,"in":"query","description":"Items per page (default: 10)","schema":{"type":"number"}}],"responses":{"200":{"description":"Property types retrieved successfully"}},"tags":["Penthouses Property Type"]}},"/api/v1/penthouses-property-type/{id}":{"get":{"operationId":"PenthousesPropertyTypeController_findOne","summary":"Get property type by ID","parameters":[{"name":"id","required":true,"in":"path","description":"Property type ID","schema":{"type":"string"}}],"responses":{"200":{"description":"Property type retrieved successfully","content":{"application/json":{"schema":{"$ref":"#/components/schemas/PenthousesPropertyTypeResponse"}}}}},"tags":["Penthouses Property Type"]},"patch":{"operationId":"PenthousesPropertyTypeController_update","summary":"Update property type","parameters":[{"name":"id","required":true,"in":"path","description":"Property type ID","schema":{"type":"string"}}],"requestBody":{"required":true,"content":{"application/json":{"schema":{"$ref":"#/components/schemas/UpdatePenthousesPropertyTypeDto"}}}},"responses":{"200":{"description":"Property type updated successfully","content":{"application/json":{"schema":{"$ref":"#/components/schemas/PenthousesPropertyTypeResponse"}}}}},"tags":["Penthouses Property Type"],"security":[{"bearer":[]}]},"delete":{"operationId":"PenthousesPropertyTypeController_remove","summary":"Delete property type","parameters":[{"name":"id","required":true,"in":"path","description":"Property type ID","schema":{"type":"string"}}],"responses":{"204":{"description":"Property type deleted successfully"}},"tags":["Penthouses Property Type"],"security":[{"bearer":[]}]}},"/api/v1/penthouses-office-type":{"get":{"operationId":"PenthousesOfficeTypeController_findAll","summary":"Get all office types","parameters":[{"name":"page","required":false,"in":"query","description":"Page number (default: 1)","schema":{"type":"number"}},{"name":"limit","required":false,"in":"query","description":"Items per page (default: 10)","schema":{"type":"number"}}],"responses":{"200":{"description":"Office types retrieved successfully"}},"tags":["Penthouses Office Type"],"security":[{"bearer":[]}]}},"/api/v1/penthouses-office-type/{id}":{"get":{"operationId":"PenthousesOfficeTypeController_findOne","summary":"Get office type by ID","parameters":[{"name":"id","required":true,"in":"path","description":"Office type ID","schema":{"type":"string"}}],"responses":{"200":{"description":"Office type retrieved successfully","content":{"application/json":{"schema":{"$ref":"#/components/schemas/PenthousesOfficeTypeResponse"}}}}},"tags":["Penthouses Office Type"],"security":[{"bearer":[]}]}},"/api/v1/penthouses-request-information":{"post":{"operationId":"PenthousesRequestInformationController_create","summary":"Submit a penthouses request information","parameters":[],"requestBody":{"required":true,"content":{"application/json":{"schema":{"$ref":"#/components/schemas/CreatePenthousesRequestInformationDto"}}}},"responses":{"201":{"description":"Request information submitted successfully","content":{"application/json":{"schema":{"$ref":"#/components/schemas/PenthousesRequestInformationResponse"}}}}},"tags":["Penthouses Request Information"],"security":[{"bearer":[]}]},"get":{"operationId":"PenthousesRequestInformationController_findAll","summary":"Get all penthouses request information","parameters":[{"name":"page","required":false,"in":"query","description":"Page number (default: 1)","schema":{"type":"number"}},{"name":"limit","required":false,"in":"query","description":"Items per page (default: 10)","schema":{"type":"number"}},{"name":"status","required":false,"in":"query","description":"Filter by status","schema":{"type":"string"}},{"name":"penthousesId","required":false,"in":"query","description":"Filter by penthouses ID","schema":{"type":"string"}}],"responses":{"200":{"description":"Request information retrieved successfully"}},"tags":["Penthouses Request Information"],"security":[{"bearer":[]}]}},"/api/v1/penthouses-request-information/statistics":{"get":{"operationId":"PenthousesRequestInformationController_getStatistics","summary":"Get penthouses request information statistics","parameters":[],"responses":{"200":{"description":"Statistics retrieved successfully"}},"tags":["Penthouses Request Information"],"security":[{"bearer":[]}]}},"/api/v1/penthouses-request-information/penthouses/{penthousesId}":{"get":{"operationId":"PenthousesRequestInformationController_findByPenthouses","summary":"Get request information by penthouses ID","parameters":[{"name":"penthousesId","required":true,"in":"path","description":"Penthouses ID","schema":{"type":"string"}}],"responses":{"200":{"description":"Request information retrieved successfully","content":{"application/json":{"schema":{"type":"array","items":{"$ref":"#/components/schemas/PenthousesRequestInformationResponse"}}}}}},"tags":["Penthouses Request Information"],"security":[{"bearer":[]}]}},"/api/v1/penthouses-request-information/{id}":{"get":{"operationId":"PenthousesRequestInformationController_findOne","summary":"Get request information by ID","parameters":[{"name":"id","required":true,"in":"path","description":"Request information ID","schema":{"type":"string"}}],"responses":{"200":{"description":"Request information retrieved successfully","content":{"application/json":{"schema":{"$ref":"#/components/schemas/PenthousesRequestInformationResponse"}}}}},"tags":["Penthouses Request Information"],"security":[{"bearer":[]}]},"patch":{"operationId":"PenthousesRequestInformationController_update","summary":"Update request information","parameters":[{"name":"id","required":true,"in":"path","description":"Request information ID","schema":{"type":"string"}}],"requestBody":{"required":true,"content":{"application/json":{"schema":{"$ref":"#/components/schemas/UpdatePenthousesRequestInformationDto"}}}},"responses":{"200":{"description":"Request information updated successfully","content":{"application/json":{"schema":{"$ref":"#/components/schemas/PenthousesRequestInformationResponse"}}}}},"tags":["Penthouses Request Information"],"security":[{"bearer":[]}]},"delete":{"operationId":"PenthousesRequestInformationController_remove","summary":"Delete request information","parameters":[{"name":"id","required":true,"in":"path","description":"Request information ID","schema":{"type":"string"}}],"responses":{"204":{"description":"Request information deleted successfully"}},"tags":["Penthouses Request Information"],"security":[{"bearer":[]}]}},"/api/v1/public/content/slug/{slug}":{"get":{"operationId":"PublicController_getContentBySlug","summary":"Get content by slug (public)","parameters":[{"name":"slug","required":true,"in":"path","description":"Content slug","schema":{"type":"string"}},{"name":"lang","required":false,"in":"query","description":"Language code (en, th)","schema":{"type":"string"}}],"responses":{"200":{"description":""}},"tags":["Public API"]}},"/api/v1/public/content/published":{"get":{"operationId":"PublicController_getPublishedContents","summary":"Get published contents (public)","parameters":[{"name":"lang","required":false,"in":"query","description":"Language code (en, th)","schema":{"type":"string"}},{"name":"category","required":false,"in":"query","description":"Category slug","schema":{"type":"string"}}],"responses":{"200":{"description":""}},"tags":["Public API"]}},"/api/v1/public/category/slug/{slug}":{"get":{"operationId":"PublicController_getCategoryBySlug","summary":"Get category by slug (public)","parameters":[{"name":"slug","required":true,"in":"path","description":"Category slug","schema":{"type":"string"}},{"name":"lang","required":false,"in":"query","description":"Language code (en, th)","schema":{"type":"string"}}],"responses":{"200":{"description":""}},"tags":["Public API"]}},"/api/v1/public/categories":{"get":{"operationId":"PublicController_getPublicCategories","summary":"Get active categories (public)","parameters":[{"name":"lang","required":false,"in":"query","description":"Language code (en, th)","schema":{"type":"string"}}],"responses":{"200":{"description":""}},"tags":["Public API"]}},"/api/v1/public/navigation":{"get":{"operationId":"PublicController_getPublicNavigation","summary":"Get public navigation menu by language","parameters":[{"name":"lang","required":false,"in":"query","description":"Language code (default: en)","schema":{"type":"string"}}],"responses":{"200":{"description":""}},"tags":["Public API"]}},"/api/v1/public/labels":{"get":{"operationId":"PublicController_getLabelsByLanguage","summary":"Get labels by language (public)","parameters":[{"name":"lang","required":false,"in":"query","description":"Language code (en, th)","schema":{"type":"string"}}],"responses":{"200":{"description":""}},"tags":["Public API"]}},"/api/v1/public/contact-form":{"post":{"operationId":"PublicController_createContactForm","summary":"Submit contact form (public)","parameters":[],"requestBody":{"required":true,"content":{"application/json":{"schema":{"$ref":"#/components/schemas/CreateContactFormDto"}}}},"responses":{"201":{"description":""}},"tags":["Public API"]}},"/api/v1/public/penthouses-request-information":{"post":{"operationId":"PublicController_createPenthousesRequestInformation","summary":"Submit penthouses request information (public)","parameters":[],"requestBody":{"required":true,"content":{"application/json":{"schema":{"$ref":"#/components/schemas/CreatePenthousesRequestInformationDto"}}}},"responses":{"201":{"description":""}},"tags":["Public API"]}},"/api/v1/public/privacy-consent":{"post":{"operationId":"PublicController_createPrivacyConsent","summary":"Submit privacy consent (public)","parameters":[],"requestBody":{"required":true,"content":{"application/json":{"schema":{"$ref":"#/components/schemas/CreatePrivacyConsentDto"}}}},"responses":{"201":{"description":""}},"tags":["Public API"]}},"/api/v1/public/penthouses":{"get":{"operationId":"PublicController_getPublishedPenthouses","summary":"Get published penthouses (public)","parameters":[{"name":"page","required":false,"in":"query","description":"Page number (default: 1)","schema":{"type":"number"}},{"name":"limit","required":false,"in":"query","description":"Items per page (default: 10)","schema":{"type":"number"}},{"name":"locationId","required":false,"in":"query","description":"Filter by location ID","schema":{"type":"string"}},{"name":"propertyTypeId","required":false,"in":"query","description":"Filter by property type ID","schema":{"type":"string"}},{"name":"offerTypeId","required":false,"in":"query","description":"Filter by offer type ID","schema":{"type":"string"}},{"name":"lang","required":false,"in":"query","description":"Language code (en, th)","schema":{"type":"string"}}],"responses":{"200":{"description":""}},"tags":["Public API"]}},"/api/v1/public/penthouses/slug/{slug}":{"get":{"operationId":"PublicController_getPenthouseBySlug","summary":"Get penthouse by slug (public)","parameters":[{"name":"slug","required":true,"in":"path","description":"Penthouse slug","schema":{"type":"string"}},{"name":"lang","required":false,"in":"query","description":"Language code (en, th)","schema":{"type":"string"}}],"responses":{"200":{"description":""}},"tags":["Public API"]}},"/api/v1/public/penthouses-locations":{"get":{"operationId":"PublicController_getPenthouseLocations","summary":"Get penthouse locations (public)","parameters":[{"name":"lang","required":false,"in":"query","description":"Language code (en, th)","schema":{"type":"string"}}],"responses":{"200":{"description":""}},"tags":["Public API"]}},"/api/v1/public/penthouses-property-types":{"get":{"operationId":"PublicController_getPenthousePropertyTypes","summary":"Get penthouse property types (public)","parameters":[{"name":"lang","required":false,"in":"query","description":"Language code (en, th)","schema":{"type":"string"}}],"responses":{"200":{"description":""}},"tags":["Public API"]}},"/api/v1/public/penthouses-offer-types":{"get":{"operationId":"PublicController_getPenthouseOfferTypes","summary":"Get penthouse offer types (public)","parameters":[{"name":"lang","required":false,"in":"query","description":"Language code (en, th)","schema":{"type":"string"}}],"responses":{"200":{"description":""}},"tags":["Public API"]}}},"info":{"title":"Jairak Demo API","description":"NestJS API with Prisma ORM and MySQL","version":"1.0","contact":{}},"tags":[],"servers":[],"components":{"securitySchemes":{"bearer":{"scheme":"bearer","bearerFormat":"JWT","type":"http"}},"schemas":{"LoginDto":{"type":"object","properties":{"email":{"type":"string","example":"admin@thailandpenthouses.com"},"password":{"type":"string","example":"admin123"}},"required":["email","password"]},"RegisterDto":{"type":"object","properties":{"email":{"type":"string","example":"user@example.com"},"username":{"type":"string","example":"username"},"password":{"type":"string","example":"Password123!"},"firstName":{"type":"string","example":"John"},"lastName":{"type":"string","example":"Doe"},"phoneNumber":{"type":"string","example":"+1234567890"}},"required":["email","password"]},"RefreshTokenDto":{"type":"object","properties":{"refreshToken":{"type":"string","example":"eyJhbGciOiJIUzI1NiIsInR5cCI6IkpXVCJ9..."}},"required":["refreshToken"]},"LogoutDto":{"type":"object","properties":{"refreshToken":{"type":"string","example":"eyJhbGciOiJIUzI1NiIsInR5cCI6IkpXVCJ9..."}}},"RolePermissionResponse":{"type":"object","properties":{"id":{"type":"string","description":"Permission ID"},"menuId":{"type":"string","description":"Menu ID"},"menuName":{"type":"string","description":"Menu name"},"menuSlug":{"type":"string","description":"Menu slug"},"menuUrl":{"type":"string","description":"Menu URL"},"canView":{"type":"boolean","description":"Can view permission"},"canCreate":{"type":"boolean","description":"Can create permission"},"canUpdate":{"type":"boolean","description":"Can update permission"},"canDelete":{"type":"boolean","description":"Can delete permission"}},"required":["id","menuId","menuName","menuSlug","menuUrl","canView","canCreate","canUpdate","canDelete"]},"MenuPermissionResponse":{"type":"object","properties":{"canView":{"type":"boolean","description":"Can view permission"},"canCreate":{"type":"boolean","description":"Can create permission"},"canUpdate":{"type":"boolean","description":"Can update permission"},"canDelete":{"type":"boolean","description":"Can delete permission"}},"required":["canView","canCreate","canUpdate","canDelete"]},"MenuItemResponse":{"type":"object","properties":{"id":{"type":"string","description":"Menu ID"},"name":{"type":"string","description":"Menu name"},"slug":{"type":"string","description":"Menu slug"},"url":{"type":"string","description":"Menu URL"},"icon":{"type":"string","description":"Menu icon"},"sortOrder":{"type":"number","description":"Menu sort order"},"permissions":{"description":"Menu permissions","allOf":[{"$ref":"#/components/schemas/MenuPermissionResponse"}]},"children":{"description":"Child menus","type":"array","items":{"$ref":"#/components/schemas/MenuItemResponse"}}},"required":["id","name","slug","url","icon","sortOrder","permissions","children"]},"RoleResponse":{"type":"object","properties":{"id":{"type":"string","description":"Role ID"},"name":{"type":"string","description":"Role name"},"description":{"type":"string","description":"Role description"},"permissions":{"description":"Role permissions (flat structure)","type":"array","items":{"$ref":"#/components/schemas/RolePermissionResponse"}},"menus":{"description":"Hierarchical menu structure (3 levels)","type":"array","items":{"$ref":"#/components/schemas/MenuItemResponse"}}},"required":["id","name","description","permissions","menus"]},"ProfileResponse":{"type":"object","properties":{"id":{"type":"string","description":"User ID"},"email":{"type":"string","description":"User email"},"username":{"type":"string","description":"Username"},"firstName":{"type":"string","description":"User first name"},"lastName":{"type":"string","description":"User last name"},"phoneNumber":{"type":"string","description":"User phone number"},"avatarUrl":{"type":"string","description":"User avatar URL"},"loginMethod":{"type":"string","description":"Login method (local, azure, etc.)"},"lastLoginDate":{"format":"date-time","type":"string","description":"Last login date"},"createdAt":{"format":"date-time","type":"string","description":"User creation timestamp"},"updatedAt":{"format":"date-time","type":"string","description":"User last update timestamp"},"role":{"description":"User role with hierarchical menu structure","allOf":[{"$ref":"#/components/schemas/RoleResponse"}]}},"required":["id","email","username","firstName","lastName","phoneNumber","avatarUrl","loginMethod","lastLoginDate","createdAt","updatedAt","role"]},"UpdateProfileDto":{"type":"object","properties":{"email":{"type":"string","example":"user@example.com"},"username":{"type":"string","example":"username"},"firstName":{"type":"string","example":"John"},"lastName":{"type":"string","example":"Doe"},"phoneNumber":{"type":"string","example":"+1234567890"},"avatarUrl":{"type":"string","example":"https://example.com/avatar.jpg"},"note":{"type":"string","example":"Additional notes about the user"}}},"CreateUserDto":{"type":"object","properties":{"email":{"type":"string","example":"user@example.com"},"username":{"type":"string","example":"username"},"password":{"type":"string","example":"password123"},"firstName":{"type":"string","example":"John"},"lastName":{"type":"string","example":"Doe"},"phoneNumber":{"type":"string","example":"+1234567890"},"avatarUrl":{"type":"string","example":"https://example.com/avatar.jpg"},"note":{"type":"string","example":"Additional notes about the user"},"roleId":{"type":"string","example":"role-id-here"}},"required":["email","roleId"]},"UpdateUserDto":{"type":"object","properties":{"email":{"type":"string","example":"user@example.com"},"username":{"type":"string","example":"username"},"password":{"type":"string","example":"password123"},"firstName":{"type":"string","example":"John"},"lastName":{"type":"string","example":"Doe"},"phoneNumber":{"type":"string","example":"+1234567890"},"avatarUrl":{"type":"string","example":"https://example.com/avatar.jpg"},"note":{"type":"string","example":"Additional notes about the user"},"roleId":{"type":"string","example":"role-id-here"}}},"CreateRoleDto":{"type":"object","properties":{"name":{"type":"string","example":"Manager"},"description":{"type":"string","example":"Manager role with limited permissions"}},"required":["name"]},"UpdateRoleDto":{"type":"object","properties":{"name":{"type":"string","example":"Manager"},"description":{"type":"string","example":"Manager role with limited permissions"}}},"PermissionDto":{"type":"object","properties":{"menuId":{"type":"string","example":"menu-id-here"},"canView":{"type":"boolean","example":true},"canCreate":{"type":"boolean","example":false},"canUpdate":{"type":"boolean","example":false},"canDelete":{"type":"boolean","example":false}},"required":["menuId","canView","canCreate","canUpdate","canDelete"]},"SetPermissionsDto":{"type":"object","properties":{"permissions":{"type":"array","items":{"$ref":"#/components/schemas/PermissionDto"}}},"required":["permissions"]},"MenuPermissionDto":{"type":"object","properties":{"id":{"type":"string","description":"Menu ID"},"name":{"type":"string","description":"Menu name"},"slug":{"type":"string","description":"Menu slug"},"icon":{"type":"string","description":"Menu icon"},"url":{"type":"string","description":"Menu URL"},"permissions":{"description":"Menu permissions","allOf":[{"$ref":"#/components/schemas/PermissionDto"}]},"children":{"description":"Child menus","type":"array","items":{"$ref":"#/components/schemas/MenuPermissionDto"}}},"required":["id","name","permissions"]},"UpdatePermissionsFromMenusDto":{"type":"object","properties":{"roleId":{"type":"string","description":"Role ID"},"permissions":{"description":"Menu permissions structure","type":"array","items":{"$ref":"#/components/schemas/MenuPermissionDto"}}},"required":["roleId","permissions"]},"TestValidationDto":{"type":"object","properties":{"testBoolean":{"type":"boolean","description":"Test boolean"}},"required":["testBoolean"]},"CreateMenuDto":{"type":"object","properties":{"name":{"type":"string","description":"Menu name"},"slug":{"type":"string","description":"Menu slug (unique identifier)"},"url":{"type":"string","description":"Menu URL"},"icon":{"type":"string","description":"Menu icon"},"parentId":{"type":"string","description":"Parent menu ID"},"sortOrder":{"type":"number","description":"Sort order","default":0},"isActive":{"type":"boolean","description":"Is active","default":true}},"required":["name","slug"]},"UpdateMenuDto":{"type":"object","properties":{"name":{"type":"string","description":"Menu name"},"slug":{"type":"string","description":"Menu slug (unique identifier)"},"url":{"type":"string","description":"Menu URL"},"icon":{"type":"string","description":"Menu icon"},"parentId":{"type":"string","description":"Parent menu ID"},"sortOrder":{"type":"number","description":"Sort order","default":0},"isActive":{"type":"boolean","description":"Is active","default":true}}},"CreateMenuTranslationDto":{"type":"object","properties":{"languageCode":{"type":"string","description":"Language code"},"name":{"type":"string","description":"Menu name in this language"},"isActive":{"type":"boolean","description":"Is active","default":true}},"required":["languageCode","name"]},"CreateCategoryDto":{"type":"object","properties":{"name":{"type":"string","description":"Category name"},"slug":{"type":"string","description":"Category slug (URL-friendly)"},"description":{"type":"string","description":"Category description"},"parentId":{"type":"string","description":"Parent category ID"},"sortOrder":{"type":"number","description":"Sort order","default":0}},"required":["name","slug"]},"UpdateCategoryDto":{"type":"object","properties":{"name":{"type":"string","description":"Category name"},"slug":{"type":"string","description":"Category slug (URL-friendly)"},"description":{"type":"string","description":"Category description"},"parentId":{"type":"string","description":"Parent category ID"},"sortOrder":{"type":"number","description":"Sort order","default":0}}},"CreateCategoryTranslationDto":{"type":"object","properties":{"languageCode":{"type":"string","description":"Language code (en, th)"},"name":{"type":"string","description":"Translated name"},"description":{"type":"string","description":"Translated description"}},"required":["languageCode","name"]},"CreateContentDto":{"type":"object","properties":{"title":{"type":"string","description":"Content title"},"slug":{"type":"string","description":"Content slug (URL-friendly)"},"content":{"type":"string","description":"Content body"},"excerpt":{"type":"string","description":"Content excerpt"},"featuredImage":{"type":"string","description":"Featured image URL"},"metaTitle":{"type":"string","description":"SEO meta title"},"metaDescription":{"type":"string","description":"SEO meta description"},"metaKeywords":{"type":"string","description":"SEO meta keywords"},"categoryId":{"type":"string","description":"Category ID"},"status":{"type":"string","description":"Content status","enum":["draft","published","archived"],"default":"draft"},"publishStartDate":{"type":"string","description":"Publish start date"},"publishEndDate":{"type":"string","description":"Publish end date"},"isVisible":{"type":"boolean","description":"Is visible","default":true}},"required":["title","slug","categoryId"]},"UpdateContentDto":{"type":"object","properties":{"title":{"type":"string","description":"Content title"},"slug":{"type":"string","description":"Content slug (URL-friendly)"},"content":{"type":"string","description":"Content body"},"excerpt":{"type":"string","description":"Content excerpt"},"featuredImage":{"type":"string","description":"Featured image URL"},"metaTitle":{"type":"string","description":"SEO meta title"},"metaDescription":{"type":"string","description":"SEO meta description"},"metaKeywords":{"type":"string","description":"SEO meta keywords"},"categoryId":{"type":"string","description":"Category ID"},"status":{"type":"string","description":"Content status","enum":["draft","published","archived"],"default":"draft"},"publishStartDate":{"type":"string","description":"Publish start date"},"publishEndDate":{"type":"string","description":"Publish end date"},"isVisible":{"type":"boolean","description":"Is visible","default":true}}},"CreateContentTranslationDto":{"type":"object","properties":{"languageCode":{"type":"string","description":"Language code (en, th)"},"title":{"type":"string","description":"Translated title"},"content":{"type":"string","description":"Translated content"},"excerpt":{"type":"string","description":"Translated excerpt"},"metaTitle":{"type":"string","description":"Translated SEO meta title"},"metaDescription":{"type":"string","description":"Translated SEO meta description"},"metaKeywords":{"type":"string","description":"Translated SEO meta keywords"}},"required":["languageCode","title"]},"CreateLabelDto":{"type":"object","properties":{"key":{"type":"string","description":"Label key"},"defaultValue":{"type":"string","description":"Default value"},"description":{"type":"string","description":"Description"},"isActive":{"type":"boolean","description":"Is active","default":true}},"required":["key","defaultValue"]},"UpdateLabelDto":{"type":"object","properties":{"key":{"type":"string","description":"Label key"},"defaultValue":{"type":"string","description":"Default value"},"description":{"type":"string","description":"Description"},"isActive":{"type":"boolean","description":"Is active","default":true}}},"CreateLabelTranslationDto":{"type":"object","properties":{"languageCode":{"type":"string","description":"Language code"},"value":{"type":"string","description":"Translation value"},"isActive":{"type":"boolean","description":"Is active","default":true}},"required":["languageCode","value"]},"CreateLanguageDto":{"type":"object","properties":{"code":{"type":"string","example":"en","description":"Language code (ISO 639-1)"},"name":{"type":"string","example":"English","description":"Language name"},"nativeName":{"type":"string","example":"English","description":"Native language name"},"flagIcon":{"type":"string","example":"","description":"Flag icon"},"isDefault":{"type":"boolean","example":false,"description":"Is default language"},"sortOrder":{"type":"number","example":0,"description":"Sort order"}},"required":["code","name","nativeName"]},"UpdateLanguageDto":{"type":"object","properties":{"code":{"type":"string","example":"en","description":"Language code (ISO 639-1)"},"name":{"type":"string","example":"English","description":"Language name"},"nativeName":{"type":"string","example":"English","description":"Native language name"},"flagIcon":{"type":"string","example":"","description":"Flag icon"},"isDefault":{"type":"boolean","example":false,"description":"Is default language"},"sortOrder":{"type":"number","example":0,"description":"Sort order"}}},"SetDefaultLanguageDto":{"type":"object","properties":{"languageId":{"type":"string","example":"clxxx123","description":"Language ID to set as default"}},"required":["languageId"]},"CreateSettingDto":{"type":"object","properties":{"key":{"type":"string","example":"app_name","description":"Setting key"},"value":{"type":"string","example":"My Application","description":"Setting value"},"description":{"type":"string","example":"Application name","description":"Setting description"},"isActive":{"type":"boolean","example":true,"description":"Is setting active"}},"required":["key"]},"UpdateSettingDto":{"type":"object","properties":{"key":{"type":"string","example":"app_name","description":"Setting key"},"value":{"type":"string","example":"My Application","description":"Setting value"},"description":{"type":"string","example":"Application name","description":"Setting description"},"isActive":{"type":"boolean","example":true,"description":"Is setting active"}}},"CreateConfigurationDto":{"type":"object","properties":{"key":{"type":"string"},"value":{"type":"string"},"description":{"type":"string"},"isEncrypted":{"type":"boolean","default":false},"isActive":{"type":"boolean","default":true}},"required":["key","value","isEncrypted"]},"UpdateConfigurationDto":{"type":"object","properties":{"key":{"type":"string"},"value":{"type":"string"},"description":{"type":"string"},"isEncrypted":{"type":"boolean","default":false},"isActive":{"type":"boolean","default":true}}},"CreateContactFormDto":{"type":"object","properties":{"firstName":{"type":"string","description":"First name","example":"John","maxLength":100},"lastName":{"type":"string","description":"Last name","example":"Doe","maxLength":100},"email":{"type":"string","description":"Email address","example":"john.doe@example.com","maxLength":100},"phoneNumber":{"type":"string","description":"Phone number","example":"+66812345678","maxLength":20},"message":{"type":"string","description":"Message content","example":"I am interested in your penthouse properties. Please contact me."},"consent":{"type":"boolean","description":"Privacy consent agreement","example":true},"consentText":{"type":"string","description":"Consent text that user agreed to","example":"I agree to the privacy policy and terms of service","maxLength":500}},"required":["firstName","lastName","email"]},"ContactFormResponse":{"type":"object","properties":{"id":{"type":"string","description":"Contact form ID","example":"cmcyw3exz0019yjv6cn1heh3l"},"firstName":{"type":"string","description":"First name","example":"John"},"lastName":{"type":"string","description":"Last name","example":"Doe"},"email":{"type":"string","description":"Email address","example":"john.doe@example.com"},"phoneNumber":{"type":"string","description":"Phone number","example":"+66812345678","nullable":true},"message":{"type":"string","description":"Message content","example":"I am interested in your penthouse properties. Please contact me.","nullable":true},"consent":{"type":"boolean","description":"Privacy consent agreement","example":true,"nullable":true},"consentText":{"type":"string","description":"Consent text that user agreed to","example":"I agree to the privacy policy and terms of service","nullable":true},"status":{"type":"string","description":"Contact form status","enum":["new","in_progress","resolved","closed"],"example":"new"},"ipAddress":{"type":"string","description":"IP address of the sender","example":"192.168.1.1","nullable":true},"userAgent":{"type":"string","description":"User agent of the sender","example":"Mozilla/5.0 (Windows NT 10.0; Win64; x64) AppleWebKit/537.36","nullable":true},"isActive":{"type":"boolean","description":"Is active","example":true},"createdBy":{"type":"string","description":"Created by user ID","example":"cmcyw3exz0001yjv6cn1heh3a","nullable":true},"createdByName":{"type":"string","description":"Created by user name","example":"System","nullable":true},"createdDate":{"format":"date-time","type":"string","description":"Created date","example":"2025-01-07T02:20:00.000Z"},"updatedBy":{"type":"string","description":"Updated by user ID","example":"cmcyw3exz0001yjv6cn1heh3a","nullable":true},"updatedByName":{"type":"string","description":"Updated by user name","example":"Admin User","nullable":true},"updatedDate":{"format":"date-time","type":"string","description":"Updated date","example":"2025-01-07T02:20:00.000Z"}},"required":["id","firstName","lastName","email","phoneNumber","message","consent","consentText","status","ipAddress","userAgent","isActive","createdBy","createdByName","createdDate","updatedBy","updatedByName","updatedDate"]},"UpdateContactFormDto":{"type":"object","properties":{"firstName":{"type":"string","description":"First name","example":"John","maxLength":100},"lastName":{"type":"string","description":"Last name","example":"Doe","maxLength":100},"email":{"type":"string","description":"Email address","example":"john.doe@example.com","maxLength":100},"phoneNumber":{"type":"string","description":"Phone number","example":"+66812345678","maxLength":20},"message":{"type":"string","description":"Message content","example":"I am interested in your penthouse properties. Please contact me."},"consent":{"type":"boolean","description":"Privacy consent agreement","example":true},"consentText":{"type":"string","description":"Consent text that user agreed to","example":"I agree to the privacy policy and terms of service","maxLength":500},"status":{"type":"string","description":"Contact form status","enum":["new","in_progress","resolved","closed"],"example":"in_progress"}}},"CreatePenthouseTranslationDto":{"type":"object","properties":{}},"CreatePenthousePriceDto":{"type":"object","properties":{}},"CreatePenthouseProjectInfoDto":{"type":"object","properties":{}},"CreatePenthouseNeighborhoodDto":{"type":"object","properties":{}},"CreatePenthouseGalleryTourDto":{"type":"object","properties":{}},"CreatePenthouseDto":{"type":"object","properties":{"title":{"type":"string","description":"Penthouse title","example":"Luxury Penthouse with City View","maxLength":255},"coverImage":{"type":"string","description":"Cover image URL","example":"https://example.com/images/penthouse1.jpg","maxLength":255},"locationId":{"type":"string","description":"Location ID","example":"cmcyw3exz0019yjv6cn1heh3l"},"propertyTypeId":{"type":"string","description":"Property type ID","example":"cmcyw3exz0019yjv6cn1heh3m"},"officeTypeId":{"type":"string","description":"Office type ID","example":"cmcyw3exz0019yjv6cn1heh3n"},"propertyPrice":{"type":"number","description":"Property price","example":"15000000.00"},"status":{"type":"string","description":"Penthouse status","enum":["draft","published","archived"],"example":"draft"},"publishStartDate":{"type":"string","description":"Publish start date","example":"2025-01-07T00:00:00.000Z"},"publishEndDate":{"type":"string","description":"Publish end date","example":"2025-12-31T23:59:59.000Z"},"translations":{"description":"Penthouse translations","type":"array","items":{"$ref":"#/components/schemas/CreatePenthouseTranslationDto"}},"prices":{"description":"Penthouse prices","type":"array","items":{"$ref":"#/components/schemas/CreatePenthousePriceDto"}},"projectInfo":{"description":"Project information sections","type":"array","items":{"$ref":"#/components/schemas/CreatePenthouseProjectInfoDto"}},"neighborhood":{"description":"Neighborhood sections","type":"array","items":{"$ref":"#/components/schemas/CreatePenthouseNeighborhoodDto"}},"galleryTour":{"description":"Gallery & Tour sections","type":"array","items":{"$ref":"#/components/schemas/CreatePenthouseGalleryTourDto"}}},"required":["title"]},"PenthouseLocationResponse":{"type":"object","properties":{"id":{"type":"string","description":"Location ID","example":"cmcyw3exz0019yjv6cn1heh3l"},"name":{"type":"string","description":"Location name","example":"Bangkok CBD"}},"required":["id","name"]},"PenthousePropertyTypeResponse":{"type":"object","properties":{"id":{"type":"string","description":"Property type ID","example":"cmcyw3exz0019yjv6cn1heh3m"},"name":{"type":"string","description":"Property type name","example":"Luxury Penthouse"}},"required":["id","name"]},"PenthouseOfficeTypeResponse":{"type":"object","properties":{"id":{"type":"string","description":"Office type ID","example":"cmcyw3exz0019yjv6cn1heh3n"},"name":{"type":"string","description":"Office type name","example":"Executive Office"}},"required":["id","name"]},"PenthouseResponse":{"type":"object","properties":{"id":{"type":"string","description":"Penthouse ID","example":"cmcyw3exz0019yjv6cn1heh3l"},"title":{"type":"string","description":"Penthouse title","example":"Luxury Penthouse with City View"},"coverImage":{"type":"string","description":"Cover image URL","example":"https://example.com/images/penthouse1.jpg","nullable":true},"locationId":{"type":"string","description":"Location ID","example":"cmcyw3exz0019yjv6cn1heh3l","nullable":true},"propertyTypeId":{"type":"string","description":"Property type ID","example":"cmcyw3exz0019yjv6cn1heh3m","nullable":true},"officeTypeId":{"type":"string","description":"Office type ID","example":"cmcyw3exz0019yjv6cn1heh3n","nullable":true},"propertyPrice":{"type":"string","description":"Property price","example":"15000000.00","nullable":true},"status":{"type":"string","description":"Penthouse status","enum":["draft","published","archived"],"example":"draft"},"publishStartDate":{"format":"date-time","type":"string","description":"Publish start date","example":"2025-01-07T00:00:00.000Z","nullable":true},"publishEndDate":{"format":"date-time","type":"string","description":"Publish end date","example":"2025-12-31T23:59:59.000Z","nullable":true},"isActive":{"type":"boolean","description":"Is active","example":true},"createdBy":{"type":"string","description":"Created by user ID","example":"cmcyw3exz0001yjv6cn1heh3a","nullable":true},"createdByName":{"type":"string","description":"Created by user name","example":"Admin User","nullable":true},"createdDate":{"format":"date-time","type":"string","description":"Created date","example":"2025-01-07T02:20:00.000Z"},"updatedBy":{"type":"string","description":"Updated by user ID","example":"cmcyw3exz0001yjv6cn1heh3a","nullable":true},"updatedByName":{"type":"string","description":"Updated by user name","example":"Admin User","nullable":true},"updatedDate":{"format":"date-time","type":"string","description":"Updated date","example":"2025-01-07T02:20:00.000Z"},"location":{"description":"Location details","nullable":true,"allOf":[{"$ref":"#/components/schemas/PenthouseLocationResponse"}]},"propertyType":{"description":"Property type details","nullable":true,"allOf":[{"$ref":"#/components/schemas/PenthousePropertyTypeResponse"}]},"officeType":{"description":"Office type details","nullable":true,"allOf":[{"$ref":"#/components/schemas/PenthouseOfficeTypeResponse"}]}},"required":["id","title","coverImage","locationId","propertyTypeId","officeTypeId","propertyPrice","status","publishStartDate","publishEndDate","isActive","createdBy","createdByName","createdDate","updatedBy","updatedByName","updatedDate","location","propertyType","officeType"]},"UpdatePenthouseDto":{"type":"object","properties":{"title":{"type":"string","description":"Penthouse title","example":"Luxury Penthouse with City View","maxLength":255},"coverImage":{"type":"string","description":"Cover image URL","example":"https://example.com/images/penthouse1.jpg","maxLength":255},"locationId":{"type":"string","description":"Location ID","example":"cmcyw3exz0019yjv6cn1heh3l"},"propertyTypeId":{"type":"string","description":"Property type ID","example":"cmcyw3exz0019yjv6cn1heh3m"},"officeTypeId":{"type":"string","description":"Office type ID","example":"cmcyw3exz0019yjv6cn1heh3n"},"propertyPrice":{"type":"number","description":"Property price","example":"15000000.00"},"status":{"type":"string","description":"Penthouse status","enum":["draft","published","archived"],"example":"draft"},"publishStartDate":{"type":"string","description":"Publish start date","example":"2025-01-07T00:00:00.000Z"},"publishEndDate":{"type":"string","description":"Publish end date","example":"2025-12-31T23:59:59.000Z"},"translations":{"description":"Penthouse translations","type":"array","items":{"$ref":"#/components/schemas/CreatePenthouseTranslationDto"}},"prices":{"description":"Penthouse prices","type":"array","items":{"$ref":"#/components/schemas/CreatePenthousePriceDto"}},"projectInfo":{"description":"Project information sections","type":"array","items":{"$ref":"#/components/schemas/CreatePenthouseProjectInfoDto"}},"neighborhood":{"description":"Neighborhood sections","type":"array","items":{"$ref":"#/components/schemas/CreatePenthouseNeighborhoodDto"}},"galleryTour":{"description":"Gallery & Tour sections","type":"array","items":{"$ref":"#/components/schemas/CreatePenthouseGalleryTourDto"}}}},"CreatePenthousesLocationDto":{"type":"object","properties":{"name":{"type":"string","description":"Location name","example":"Bangkok CBD","maxLength":100}},"required":["name"]},"PenthousesLocationResponse":{"type":"object","properties":{"id":{"type":"string","description":"Location ID","example":"cmcyw3exz0019yjv6cn1heh3l"},"name":{"type":"string","description":"Location name","example":"Bangkok CBD"},"isActive":{"type":"boolean","description":"Is active","example":true},"createdBy":{"type":"string","description":"Created by user ID","example":"cmcyw3exz0001yjv6cn1heh3a","nullable":true},"createdByName":{"type":"string","description":"Created by user name","example":"Admin User","nullable":true},"createdDate":{"format":"date-time","type":"string","description":"Created date","example":"2025-01-07T02:20:00.000Z"},"updatedBy":{"type":"string","description":"Updated by user ID","example":"cmcyw3exz0001yjv6cn1heh3a","nullable":true},"updatedByName":{"type":"string","description":"Updated by user name","example":"Admin User","nullable":true},"updatedDate":{"format":"date-time","type":"string","description":"Updated date","example":"2025-01-07T02:20:00.000Z"}},"required":["id","name","isActive","createdBy","createdByName","createdDate","updatedBy","updatedByName","updatedDate"]},"UpdatePenthousesLocationDto":{"type":"object","properties":{"name":{"type":"string","description":"Location name","example":"Bangkok CBD","maxLength":100}}},"CreatePenthousesPropertyTypeDto":{"type":"object","properties":{"name":{"type":"string","description":"Property type name","example":"Luxury Penthouse","maxLength":100}},"required":["name"]},"PenthousesPropertyTypeResponse":{"type":"object","properties":{"id":{"type":"string","description":"Property type ID","example":"cmcyw3exz0019yjv6cn1heh3l"},"name":{"type":"string","description":"Property type name","example":"Luxury Penthouse"},"isActive":{"type":"boolean","description":"Is active","example":true},"createdBy":{"type":"string","description":"Created by user ID","example":"cmcyw3exz0001yjv6cn1heh3a","nullable":true},"createdByName":{"type":"string","description":"Created by user name","example":"Admin User","nullable":true},"createdDate":{"format":"date-time","type":"string","description":"Created date","example":"2025-01-07T02:20:00.000Z"},"updatedBy":{"type":"string","description":"Updated by user ID","example":"cmcyw3exz0001yjv6cn1heh3a","nullable":true},"updatedByName":{"type":"string","description":"Updated by user name","example":"Admin User","nullable":true},"updatedDate":{"format":"date-time","type":"string","description":"Updated date","example":"2025-01-07T02:20:00.000Z"}},"required":["id","name","isActive","createdBy","createdByName","createdDate","updatedBy","updatedByName","updatedDate"]},"UpdatePenthousesPropertyTypeDto":{"type":"object","properties":{"name":{"type":"string","description":"Property type name","example":"Luxury Penthouse","maxLength":100}}},"PenthousesOfficeTypeResponse":{"type":"object","properties":{"id":{"type":"string","description":"Office type ID","example":"cmcyw3exz0019yjv6cn1heh3l"},"name":{"type":"string","description":"Office type name","example":"Executive Office"},"isActive":{"type":"boolean","description":"Is active","example":true},"createdBy":{"type":"string","description":"Created by user ID","example":"cmcyw3exz0001yjv6cn1heh3a","nullable":true},"createdByName":{"type":"string","description":"Created by user name","example":"Admin User","nullable":true},"createdDate":{"format":"date-time","type":"string","description":"Created date","example":"2025-01-07T02:20:00.000Z"},"updatedBy":{"type":"string","description":"Updated by user ID","example":"cmcyw3exz0001yjv6cn1heh3a","nullable":true},"updatedByName":{"type":"string","description":"Updated by user name","example":"Admin User","nullable":true},"updatedDate":{"format":"date-time","type":"string","description":"Updated date","example":"2025-01-07T02:20:00.000Z"}},"required":["id","name","isActive","createdBy","createdByName","createdDate","updatedBy","updatedByName","updatedDate"]},"CreatePenthousesRequestInformationDto":{"type":"object","properties":{"penthousesId":{"type":"string","description":"Penthouses ID","example":"clxxxxx123456789"},"firstName":{"type":"string","description":"First name","example":"John","maxLength":100},"lastName":{"type":"string","description":"Last name","example":"Doe","maxLength":100},"email":{"type":"string","description":"Email address","example":"john.doe@example.com","maxLength":100},"phoneNumber":{"type":"string","description":"Phone number","example":"+66812345678","maxLength":20},"message":{"type":"string","description":"Message content","example":"I am interested in this penthouse property. Please contact me."},"tourType":{"type":"string","description":"Tour type preference","example":"on_site","enum":["on_site","virtual"]},"firstAvailability":{"type":"string","description":"First availability date","example":"2024-01-15T10:00:00.000Z"},"hourPreference":{"type":"string","description":"Hour preference","example":"Morning (9:00-12:00)","maxLength":50},"newsletterSignup":{"type":"boolean","description":"Newsletter signup agreement","example":true}},"required":["penthousesId","firstName","lastName","email"]},"PenthousesRequestInformationResponse":{"type":"object","properties":{"id":{"type":"string","description":"Request information ID","example":"cmcyw3exz0019yjv6cn1heh3l"},"penthousesId":{"type":"string","description":"Penthouses ID","example":"cmcyw3exz0019yjv6cn1heh3l"},"firstName":{"type":"string","description":"First name","example":"John"},"lastName":{"type":"string","description":"Last name","example":"Doe"},"email":{"type":"string","description":"Email address","example":"john.doe@example.com"},"phoneNumber":{"type":"string","description":"Phone number","example":"+66812345678","nullable":true},"message":{"type":"string","description":"Message content","example":"I am interested in this penthouse. Please provide more information.","nullable":true},"tourType":{"type":"string","description":"Tour type preference","enum":["on_site","virtual"],"example":"on_site","nullable":true},"firstAvailability":{"format":"date-time","type":"string","description":"First availability date","example":"2025-01-15T10:00:00.000Z","nullable":true},"hourPreference":{"type":"string","description":"Hour preference","example":"Morning (9:00 AM - 12:00 PM)","nullable":true},"newsletterSignup":{"type":"boolean","description":"Newsletter signup","example":false},"status":{"type":"string","description":"Request status","enum":["new","in_progress","resolved","closed"],"example":"new"},"ipAddress":{"type":"string","description":"IP address of the sender","example":"192.168.1.1","nullable":true},"userAgent":{"type":"string","description":"User agent of the sender","example":"Mozilla/5.0 (Windows NT 10.0; Win64; x64) AppleWebKit/537.36","nullable":true},"isActive":{"type":"boolean","description":"Is active","example":true},"createdBy":{"type":"string","description":"Created by user ID","example":"cmcyw3exz0001yjv6cn1heh3a","nullable":true},"createdByName":{"type":"string","description":"Created by user name","example":"System","nullable":true},"createdDate":{"format":"date-time","type":"string","description":"Created date","example":"2025-01-07T02:20:00.000Z"},"updatedBy":{"type":"string","description":"Updated by user ID","example":"cmcyw3exz0001yjv6cn1heh3a","nullable":true},"updatedByName":{"type":"string","description":"Updated by user name","example":"Admin User","nullable":true},"updatedDate":{"format":"date-time","type":"string","description":"Updated date","example":"2025-01-07T02:20:00.000Z"},"penthouses":{"type":"object","description":"Penthouses information","nullable":true}},"required":["id","penthousesId","firstName","lastName","email","phoneNumber","message","tourType","firstAvailability","hourPreference","newsletterSignup","status","ipAddress","userAgent","isActive","createdBy","createdByName","createdDate","updatedBy","updatedByName","updatedDate","penthouses"]},"UpdatePenthousesRequestInformationDto":{"type":"object","properties":{"penthousesId":{"type":"string","description":"Penthouses ID","example":"cmcyw3exz0019yjv6cn1heh3l"},"firstName":{"type":"string","description":"First name","example":"John","maxLength":100},"lastName":{"type":"string","description":"Last name","example":"Doe","maxLength":100},"email":{"type":"string","description":"Email address","example":"john.doe@example.com","maxLength":100},"phoneNumber":{"type":"string","description":"Phone number","example":"+66812345678","maxLength":20},"message":{"type":"string","description":"Message content","example":"I am interested in this penthouse. Please provide more information."},"tourType":{"type":"string","description":"Tour type preference","enum":["on_site","virtual"],"example":"on_site"},"firstAvailability":{"type":"string","description":"First availability date","example":"2025-01-15T10:00:00.000Z"},"hourPreference":{"type":"string","description":"Hour preference","example":"Morning (9:00 AM - 12:00 PM)","maxLength":50},"newsletterSignup":{"type":"boolean","description":"Newsletter signup","example":false},"status":{"type":"string","description":"Request status","enum":["new","in_progress","resolved","closed"],"example":"new"}}},"CreatePrivacyConsentDto":{"type":"object","properties":{"consentVersion":{"type":"string","description":"Consent version","example":"1.0"},"consentPreferencesStrictlyNecessaryCookies":{"type":"boolean","description":"Strictly necessary cookies consent","example":true},"consentPreferencesMarketingCookies":{"type":"boolean","description":"Marketing cookies consent","example":false},"consentPreferencesAnalyticsCookies":{"type":"boolean","description":"Analytics cookies consent","example":false},"consentPreferencesTargetingCookies":{"type":"boolean","description":"Targeting cookies consent","example":false},"action":{"type":"string","description":"Action type (accept, reject, customize)","example":"accept"},"consentTextsStrictlyNecessaryCookies":{"type":"string","description":"Strictly necessary cookies consent text","example":"These cookies are essential for the website to function properly."},"consentTextsMarketingCookies":{"type":"string","description":"Marketing cookies consent text","example":"These cookies are used for marketing purposes."},"consentTextsAnalyticsCookies":{"type":"string","description":"Analytics cookies consent text","example":"These cookies help us analyze website usage."},"consentTextsTargetingCookies":{"type":"string","description":"Targeting cookies consent text","example":"These cookies are used for targeted advertising."},"descriptionText":{"type":"string","description":"Description text","example":"We use cookies to enhance your browsing experience."}},"required":["consentVersion","consentPreferencesStrictlyNecessaryCookies","consentPreferencesMarketingCookies","consentPreferencesAnalyticsCookies","consentPreferencesTargetingCookies","action","consentTextsStrictlyNecessaryCookies","consentTextsMarketingCookies","consentTextsAnalyticsCookies","consentTextsTargetingCookies","descriptionText"]}}}}